ccscanner/__init__.py
ccscanner/scanner.py
ccscanner/extractors/__init__.py
ccscanner/extractors/autoconf_extractor.py
ccscanner/extractors/bazel_extractor.py
ccscanner/extractors/buck_extractor.py
ccscanner/extractors/buckaroo_extractor.py
ccscanner/extractors/build2_extractor.py
ccscanner/extractors/clib_extractor.py
ccscanner/extractors/cmake_extractor.py
ccscanner/extractors/conan_extractor.py
ccscanner/extractors/control_extractor.py
ccscanner/extractors/cpm_analyzer.py
ccscanner/extractors/cyclonedx_extractor.py
ccscanner/extractors/dds_extractor.py
ccscanner/extractors/dependency.py
ccscanner/extractors/extractor.py
ccscanner/extractors/hunter_analyzer.py
ccscanner/extractors/make_extractor.py
ccscanner/extractors/meson_extractor.py
ccscanner/extractors/ms_extractor.py
ccscanner/extractors/pkg_extractor.py
ccscanner/extractors/submodule_extractor.py
ccscanner/extractors/utils.py
ccscanner/extractors/vcpkg_extractor.py
ccscanner/extractors/xmake_extractor.py
ccscanner/utils/__init__.py
ccscanner/utils/utils.py
ccscanner/utils/version.py
ccscanner/utils/cmakelists_parsing/__init__.py
ccscanner/utils/cmakelists_parsing/cmake_pprint.py
ccscanner/utils/cmakelists_parsing/list_utils.py
ccscanner/utils/cmakelists_parsing/parsing.py
ccscanner/utils/cmakelists_parsing/rand.py
ccscanner-0.2.0.dist-info/METADATA
ccscanner-0.2.0.dist-info/WHEEL
ccscanner-0.2.0.dist-info/entry_points.txt
ccscanner-0.2.0.dist-info/top_level.txt
ccscanner-0.2.0.dist-info/RECORD
