Metadata-Version: 2.1
Name: ccscanner
Version: 0.2.0
Summary: A SBOM scanner for C/C++
Author: anonymous repo
Author-email: 
License: UNKNOWN
Platform: UNKNOWN
Classifier: Programming Language :: Python :: 3
Classifier: License :: OSI Approved :: MIT License
Classifier: Operating System :: OS Independent
Requires-Python: >=3.6
Requires-Dist: json5 (==0.9.9)
Requires-Dist: bs4 (==0.0.1)
Requires-Dist: GitPython
Requires-Dist: lxml
